coloury/__init__.py
coloury-7.7.7.dist-info/LICENSE.txt
coloury-7.7.7.dist-info/METADATA
coloury-7.7.7.dist-info/WHEEL
coloury-7.7.7.dist-info/top_level.txt
coloury-7.7.7.dist-info/RECORD
