Metadata-Version: 2.1
Name: coloury
Version: 7.7.7
Summary: Make your ASCII art beautiful!
Home-page: https://github.com/CodeIntelligenceAgency
Author: Cyanraze
Author-email: cyan@cia.works
License: MIT
Keywords: coloury
Classifier: Development Status :: 3 - Alpha
Classifier: Intended Audience :: Education
Classifier: Operating System :: Microsoft :: Windows :: Windows 10
Classifier: License :: OSI Approved :: MIT License
Classifier: Programming Language :: Python :: 3.9
License-File: LICENSE.txt
